setup.py
django_simple_polymorph.egg-info/PKG-INFO
django_simple_polymorph.egg-info/SOURCES.txt
django_simple_polymorph.egg-info/dependency_links.txt
django_simple_polymorph.egg-info/top_level.txt
simple_polymorph/__init__.py