Metadata-Version: 1.0
Name: django-simple-polymorph
Version: 0.4
Summary: A simple utility to polymorph inherited models
Home-page: https://bitbucket.org/freakypie/django-simple-polymorph
Author: Danemco, LLC
Author-email: dev@velocitywebworks.com
License: UNKNOWN
Platform: UNKNOWN
